readlargefile/__init__.py
readlargefile/line_reader.py
readlargefile-1.0.4.dist-info/LICENSE
readlargefile-1.0.4.dist-info/METADATA
readlargefile-1.0.4.dist-info/WHEEL
readlargefile-1.0.4.dist-info/top_level.txt
readlargefile-1.0.4.dist-info/RECORD
